{"properties":["edad","generatesMovements","genero","isAutoEmitted","isNotifiable","tasaMortalidad"],"components":[{"label":"Generates movements?","tableView":false,"defaultValue":false,"key":"generatesMovements","type":"samanCheckbox","input":true},{"label":"Is Auto Emitted?","tableView":false,"key":"isAutoEmitted","type":"samanCheckbox","input":true,"defaultValue":false},{"label":"Is Notifiable?","tableView":false,"key":"isNotifiable","type":"samanCheckbox","input":true,"defaultValue":false},{"label":"edad","applyMaskOn":"change","mask":false,"tableView":false,"arbitraryPrecision":false,"delimiter":false,"requireDecimal":false,"inputFormat":"plain","truncateMultipleSpaces":false,"key":"edad","type":"samanNumber","input":true},{"label":"genero","widget":"choicesjs","tableView":true,"data":{"values":[{"label":"M","value":"M"},{"label":"F","value":"F"}]},"valueProperty":"id","validate":{"select":false},"key":"genero","type":"samanSelect","searchField":"label__regex","authenticate":true,"input":true,"idPath":"value"},{"label":"Tasa Mortalidad","applyMaskOn":"change","mask":false,"disabled":true,"tableView":false,"arbitraryPrecision":false,"delimiter":false,"requireDecimal":false,"inputFormat":"plain","truncateMultipleSpaces":false,"key":"tasaMortalidad","type":"samanNumber","input":true}]}